{
  "generatedAt": "2025-09-09T18:58:28.501Z",
  "seasonId": 2025,
  "nextMatchday": 1,
  "iterations": 20000,
  "teams": {
    "FCB": {
      "record": {
        "wins": 0,
        "losses": 0,
        "games": 0
      },
      "top8Pct": 24.7,
      "bottom2Pct": 21.2,
      "rankPct": {
        "1": 1.4,
        "2": 2,
        "3": 2.7,
        "4": 3,
        "5": 3.3,
        "6": 3.8,
        "7": 4.1,
        "8": 4.3,
        "9": 4.9,
        "10": 5.7,
        "11": 5.7,
        "12": 6.5,
        "13": 6.9,
        "14": 7.5,
        "15": 7.8,
        "16": 9.2,
        "17": 10,
        "18": 11.2
      }
    },
    "ULM": {
      "record": {
        "wins": 0,
        "losses": 0,
        "games": 0
      },
      "top8Pct": 45.8,
      "bottom2Pct": 10.6,
      "rankPct": {
        "1": 5.9,
        "2": 6,
        "3": 5.8,
        "4": 5.6,
        "5": 5.6,
        "6": 5.9,
        "7": 5.4,
        "8": 5.6,
        "9": 5.8,
        "10": 5.4,
        "11": 5.3,
        "12": 5.6,
        "13": 5.5,
        "14": 5.4,
        "15": 5.4,
        "16": 5.3,
        "17": 5.3,
        "18": 5.3
      }
    },
    "HDB": {
      "record": {
        "wins": 0,
        "losses": 0,
        "games": 0
      },
      "top8Pct": 48,
      "bottom2Pct": 9.7,
      "rankPct": {
        "1": 6.9,
        "2": 6,
        "3": 6.1,
        "4": 5.8,
        "5": 5.8,
        "6": 6,
        "7": 5.7,
        "8": 5.6,
        "9": 5.6,
        "10": 5.1,
        "11": 5.8,
        "12": 5.6,
        "13": 5.3,
        "14": 5.1,
        "15": 5.2,
        "16": 4.6,
        "17": 4.9,
        "18": 4.8
      }
    },
    "WUE": {
      "record": {
        "wins": 0,
        "losses": 0,
        "games": 0
      },
      "top8Pct": 43.2,
      "bottom2Pct": 11.9,
      "rankPct": {
        "1": 5.1,
        "2": 5.5,
        "3": 5.2,
        "4": 5.5,
        "5": 5.3,
        "6": 5.5,
        "7": 5.6,
        "8": 5.6,
        "9": 5.4,
        "10": 5.4,
        "11": 5.6,
        "12": 5.5,
        "13": 5.8,
        "14": 5.5,
        "15": 5.9,
        "16": 5.7,
        "17": 6.2,
        "18": 5.8
      }
    },
    "BRA": {
      "record": {
        "wins": 0,
        "losses": 0,
        "games": 0
      },
      "top8Pct": 47.4,
      "bottom2Pct": 10,
      "rankPct": {
        "1": 6.3,
        "2": 6.1,
        "3": 6.1,
        "4": 5.9,
        "5": 5.6,
        "6": 6,
        "7": 5.7,
        "8": 5.7,
        "9": 5.3,
        "10": 5.7,
        "11": 5.5,
        "12": 5.5,
        "13": 5.4,
        "14": 5.3,
        "15": 5.1,
        "16": 4.8,
        "17": 5,
        "18": 5
      }
    },
    "CHE": {
      "record": {
        "wins": 0,
        "losses": 0,
        "games": 0
      },
      "top8Pct": 48.2,
      "bottom2Pct": 9.3,
      "rankPct": {
        "1": 6.7,
        "2": 6.4,
        "3": 6.5,
        "4": 5.7,
        "5": 5.9,
        "6": 5.8,
        "7": 5.6,
        "8": 5.6,
        "9": 5.5,
        "10": 5.4,
        "11": 5.3,
        "12": 5.5,
        "13": 5.3,
        "14": 5.1,
        "15": 5.3,
        "16": 5.1,
        "17": 4.7,
        "18": 4.6
      }
    },
    "BER": {
      "record": {
        "wins": 0,
        "losses": 0,
        "games": 0
      },
      "top8Pct": 43.3,
      "bottom2Pct": 10.9,
      "rankPct": {
        "1": 5,
        "2": 5.5,
        "3": 5.6,
        "4": 5.4,
        "5": 5.4,
        "6": 5.4,
        "7": 5.7,
        "8": 5.4,
        "9": 5.9,
        "10": 5.9,
        "11": 5.4,
        "12": 5.7,
        "13": 5.7,
        "14": 5.8,
        "15": 5.8,
        "16": 5.5,
        "17": 5.7,
        "18": 5.2
      }
    },
    "MBC": {
      "record": {
        "wins": 0,
        "losses": 0,
        "games": 0
      },
      "top8Pct": 47.4,
      "bottom2Pct": 9.8,
      "rankPct": {
        "1": 6.5,
        "2": 6.2,
        "3": 6,
        "4": 6,
        "5": 5.7,
        "6": 5.9,
        "7": 5.4,
        "8": 5.6,
        "9": 5.6,
        "10": 5.1,
        "11": 5.3,
        "12": 5.5,
        "13": 5.7,
        "14": 5.2,
        "15": 5.1,
        "16": 5.2,
        "17": 4.9,
        "18": 5
      }
    },
    "OLD": {
      "record": {
        "wins": 0,
        "losses": 0,
        "games": 0
      },
      "top8Pct": 46.9,
      "bottom2Pct": 10.2,
      "rankPct": {
        "1": 6.2,
        "2": 6.2,
        "3": 5.7,
        "4": 6,
        "5": 5.8,
        "6": 5.8,
        "7": 5.7,
        "8": 5.5,
        "9": 5.8,
        "10": 5.2,
        "11": 5.2,
        "12": 5.4,
        "13": 5.3,
        "14": 5.4,
        "15": 5.2,
        "16": 5.4,
        "17": 5,
        "18": 5.2
      }
    },
    "HRO": {
      "record": {
        "wins": 0,
        "losses": 0,
        "games": 0
      },
      "top8Pct": 43,
      "bottom2Pct": 11.2,
      "rankPct": {
        "1": 4.7,
        "2": 5.2,
        "3": 5.2,
        "4": 5.4,
        "5": 5.6,
        "6": 5.4,
        "7": 5.9,
        "8": 5.6,
        "9": 5.8,
        "10": 5.8,
        "11": 5.7,
        "12": 5.5,
        "13": 5.7,
        "14": 5.8,
        "15": 5.7,
        "16": 5.7,
        "17": 5.5,
        "18": 5.7
      }
    },
    "LUD": {
      "record": {
        "wins": 0,
        "losses": 0,
        "games": 0
      },
      "top8Pct": 41.9,
      "bottom2Pct": 12.2,
      "rankPct": {
        "1": 4.7,
        "2": 4.8,
        "3": 5.1,
        "4": 5.3,
        "5": 5.7,
        "6": 5.3,
        "7": 5.5,
        "8": 5.5,
        "9": 5.5,
        "10": 6,
        "11": 5.6,
        "12": 5.8,
        "13": 5.7,
        "14": 5.7,
        "15": 5.7,
        "16": 6,
        "17": 6,
        "18": 6.2
      }
    },
    "VEC": {
      "record": {
        "wins": 0,
        "losses": 0,
        "games": 0
      },
      "top8Pct": 43.9,
      "bottom2Pct": 11.1,
      "rankPct": {
        "1": 5.2,
        "2": 5.6,
        "3": 5.6,
        "4": 5.4,
        "5": 5.5,
        "6": 5.7,
        "7": 5.5,
        "8": 5.4,
        "9": 5.7,
        "10": 5.5,
        "11": 5.8,
        "12": 5.8,
        "13": 5.5,
        "14": 5.6,
        "15": 5.7,
        "16": 5.5,
        "17": 5.6,
        "18": 5.5
      }
    },
    "HAM": {
      "record": {
        "wins": 0,
        "losses": 0,
        "games": 0
      },
      "top8Pct": 42.7,
      "bottom2Pct": 11.4,
      "rankPct": {
        "1": 4.8,
        "2": 4.8,
        "3": 5.2,
        "4": 5.5,
        "5": 5.5,
        "6": 5.3,
        "7": 5.9,
        "8": 5.7,
        "9": 5.7,
        "10": 6.2,
        "11": 5.5,
        "12": 5.2,
        "13": 6,
        "14": 5.6,
        "15": 5.8,
        "16": 5.8,
        "17": 5.9,
        "18": 5.5
      }
    },
    "BON": {
      "record": {
        "wins": 0,
        "losses": 0,
        "games": 0
      },
      "top8Pct": 49.4,
      "bottom2Pct": 9.4,
      "rankPct": {
        "1": 7,
        "2": 6.8,
        "3": 6.1,
        "4": 6.6,
        "5": 5.9,
        "6": 5.8,
        "7": 5.4,
        "8": 5.7,
        "9": 5.5,
        "10": 5.3,
        "11": 5.3,
        "12": 5.2,
        "13": 5,
        "14": 5,
        "15": 4.9,
        "16": 5,
        "17": 4.9,
        "18": 4.6
      }
    },
    "BAM": {
      "record": {
        "wins": 0,
        "losses": 0,
        "games": 0
      },
      "top8Pct": 47.3,
      "bottom2Pct": 9.7,
      "rankPct": {
        "1": 6.5,
        "2": 5.8,
        "3": 5.8,
        "4": 5.6,
        "5": 6.2,
        "6": 5.8,
        "7": 5.9,
        "8": 5.7,
        "9": 5.3,
        "10": 5.6,
        "11": 5.5,
        "12": 5.3,
        "13": 5.2,
        "14": 5.8,
        "15": 5.1,
        "16": 5.1,
        "17": 4.9,
        "18": 4.8
      }
    },
    "FRS": {
      "record": {
        "wins": 0,
        "losses": 0,
        "games": 0
      },
      "top8Pct": 46.3,
      "bottom2Pct": 10.3,
      "rankPct": {
        "1": 5.9,
        "2": 5.9,
        "3": 6.1,
        "4": 5.8,
        "5": 5.7,
        "6": 5.4,
        "7": 5.8,
        "8": 5.8,
        "9": 5.6,
        "10": 5.5,
        "11": 5.8,
        "12": 5.3,
        "13": 5.3,
        "14": 5.3,
        "15": 5.2,
        "16": 5.3,
        "17": 5,
        "18": 5.3
      }
    },
    "TRI": {
      "record": {
        "wins": 0,
        "losses": 0,
        "games": 0
      },
      "top8Pct": 44.6,
      "bottom2Pct": 10.9,
      "rankPct": {
        "1": 5.6,
        "2": 5.4,
        "3": 5.4,
        "4": 5.5,
        "5": 5.6,
        "6": 5.6,
        "7": 5.6,
        "8": 5.9,
        "9": 5.5,
        "10": 5.5,
        "11": 5.9,
        "12": 5.7,
        "13": 5.4,
        "14": 5.5,
        "15": 5.7,
        "16": 5.3,
        "17": 5.5,
        "18": 5.4
      }
    },
    "JEN": {
      "record": {
        "wins": 0,
        "losses": 0,
        "games": 0
      },
      "top8Pct": 46.1,
      "bottom2Pct": 10.1,
      "rankPct": {
        "1": 5.6,
        "2": 5.9,
        "3": 5.8,
        "4": 5.8,
        "5": 6,
        "6": 5.6,
        "7": 5.6,
        "8": 5.8,
        "9": 5.7,
        "10": 5.7,
        "11": 5.7,
        "12": 5.5,
        "13": 5.3,
        "14": 5.5,
        "15": 5.3,
        "16": 5.2,
        "17": 5.1,
        "18": 5
      }
    }
  }
}